Workbook

Sheet README
A1: EV Fleet Real Options Model, India
A3: Question: should an Indian regional trucking operator switch to an electric
A4: truck now, wait and decide later, or never switch, given diesel price risk?
A6: Real, sourced inputs (see Inputs sheet notes for each):
A7: - Ashok Leyland AVTR 1920 HG (diesel) vs Tata Prima E.28K (EV) ex-showroom prices
A8: - Real fuel mileage / battery range specifications
A9: - Diesel price volatility and drift calibrated from real Indian retail diesel
A10: price history, 2015-2026 (post fuel-price-deregulation window)
A12: The India-specific finding this calibration produces:
A13: Annual volatility is only 7.0% (vs ~43% for crude oil itself)
A14: but drift is a strong +5.1%/year -- diesel prices in India are
A15: administered and historically stable in percentage terms, but have risen
... A30: Generated by excel/build_model.py. Safe to edit; regenerate to reset.

Sheet Inputs
A1: Assumptions (yellow = editable)
A3: DIESEL TRUCK -- Ashok Leyland AVTR 1920 HG
A4: Diesel truck price (capex) | B4: 2550000 | C4: Real, sourced: AVTR series ex-showroom, mid-range (cardekho/trucksfloor, 2026)
A5: Fuel efficiency | B5: 5.5 | C5: Real, sourced: AVTR 1920 HG rated mileage, 5-6 km/L (trucksbuses.com)
A6: Diesel maintenance and tires | B6: 4 | C6: Estimate: typical Indian heavy-truck upkeep, Rs per km
A7: EV TRUCK -- Tata Prima E.28K
A8: EV truck price (capex) | B8: 4000000 | C8: Real, sourced: ex-showroom range Rs 35-45 lakh, midpoint (multiple dealer sources, 2026)
A9: Charging infra (allocated) | B9: 300000 | C9: Estimate: depot DC fast charger, allocated per truck
A10: Battery capacity | B10: 453 | C10: Real, sourced: Tata Prima E.28K spec sheet, kWh
A11: Real-world range per charge | B11: 175 | C11: Real, sourced: 150-200 km spec range, midpoint, km
A12: Electricity price | B12: 7.5 | C12: Estimate: representative Indian industrial/commercial tariff, Rs per kWh (rates vary 0.9-14 by state/tier)
A13: EV maintenance and tires | B13: 2 | C13: Estimate: EV heavy trucks, fewer moving parts than diesel, Rs per km
A14: SHARED (same duty cycle both powertrains -- see README scope note)
A15: Annual distance | B15: 90000 | C15: Estimate: regional/return-to-base duty cycle, km per truck per year
A16: Freight rate | B16: 40 | C16: Estimate: representative regional full-truck-load rate, Rs per km
A17: Annual fixed overhead | B17: 60000 | C17: Estimate: insurance, permits, admin, Rs per year
A18: Discount rate | B18: 0.12 | C18: India corporate WACC, higher cost of capital than US
A19: DIESEL PRICE -- CALIBRATED FROM REAL DATA
A20: Diesel price today | B20: 98 | C20: Real: 2026 average retail price, Rs per litre (cleartax.in)
A21: Annual volatility (sigma) | B21: 0.069910436 | C21: CALIBRATED from real 2015-2026 India diesel price history, see data/calibrate_volatility.py
A22: Annual drift (mu) | B22: 0.05126461 | C22: CALIBRATED from the same real history -- India's steady multi-decade price rise
A23: DERIVED
A24: Up factor (u) | B24: =EXP(B21)
A25: Down factor (d) | B25: =1/B24
A26: Up-move probability (drift-matched, physical) | B26: =(EXP(B22)-B25)/(B24-B25) | C26: Chosen so the lattice reproduces the real drift, not just volatility
A27: EV energy efficiency (derived) | B27: =B10/B11 | C27: kWh per km = battery capacity / real-world range

Sheet Lattice
A1: Diesel price binomial lattice (Rs per litre). Node (t,i): i = number of down-moves.
A3: Down-moves i \ Year t | B3: 0 | C3: 1 | D3: 2 | E3: 3 | F3: 4 | G3: 5
B4: =Inputs!$B$20 | C4: =B4*Inputs!$B$24 | D4: =C4*Inputs!$B$24 | E4: =D4*Inputs!$B$24 | F4: =E4*Inputs!$B$24 | G4: =F4*Inputs!$B$24
C5: =B4*Inputs!$B$25 | D5: =C4*Inputs!$B$25 | E5: =D4*Inputs!$B$25 | F5: =E4*Inputs!$B$25 | G5: =F4*Inputs!$B$25
D6: =C5*Inputs!$B$25 | E6: =D5*Inputs!$B$25 | F6: =E5*Inputs!$B$25 | G6: =F5*Inputs!$B$25
E7: =D6*Inputs!$B$25 | F7: =E6*Inputs!$B$25 | G7: =F6*Inputs!$B$25
F8: =E7*Inputs!$B$25 | G8: =F7*Inputs!$B$25
G9: =F8*Inputs!$B$25

Sheet DecisionTree
A1: Cash flows and backward-induction option value (Rs)
A2: Every 'invest' value uses a FULL fresh truck life from that decision point, not the remaining life since year 0 -- a truck bought in year 3 gets its own 8 years, matching how a real purchase works.
A4: Diesel annual cash flow if operating a diesel truck, CF_diesel(t,i) | B4: Year 0 | C4: Year 1 | D4: Year 2 | E4: Year 3 | F4: Year 4 | G4: Year 5
B5: =Inputs!$B$15*(Inputs!$B$16-Lattice!B4/Inputs!$B$5-Inputs!$B$6)-Inputs!$B$17 | C5: =Inputs!$B$15*(Inputs!$B$16-Lattice!C4/Inputs!$B$5-Inputs!$B$6)-Inputs!$B$17 | D5: =Inputs!$B$15*(Inputs!$B$16-Lattice!D4/Inputs!$B$5-Inputs!$B$6)-Inputs!$B$17 | E5: =Inputs!$B$15*(Inputs!$B$16-Lattice!E4/Inputs!$B$5-Inputs!$B$6)-Inputs!$B$17 | F5: =Inputs!$B$15*(Inputs!$B$16-Lattice!F4/Inputs!$B$5-Inputs!$B$6)-Inputs!$B$17 | G5: =Inputs!$B$15*(Inputs!$B$16-Lattice!G4/Inputs!$B$5-Inputs!$B$6)-Inputs!$B$17
C6: =Inputs!$B$15*(Inputs!$B$16-Lattice!C5/Inputs!$B$5-Inputs!$B$6)-Inputs!$B$17 | D6: =Inputs!$B$15*(Inputs!$B$16-Lattice!D5/Inputs!$B$5-Inputs!$B$6)-Inputs!$B$17 | E6: =Inputs!$B$15*(Inputs!$B$16-Lattice!E5/Inputs!$B$5-Inputs!$B$6)-Inputs!$B$17 | F6: =Inputs!$B$15*(Inputs!$B$16-Lattice!F5/Inputs!$B$5-Inputs!$B$6)-Inputs!$B$17 | G6: =Inputs!$B$15*(Inputs!$B$16-Lattice!G5/Inputs!$B$5-Inputs!$B$6)-Inputs!$B$17
D7: =Inputs!$B$15*(Inputs!$B$16-Lattice!D6/Inputs!$B$5-Inputs!$B$6)-Inputs!$B$17 | E7: =Inputs!$B$15*(Inputs!$B$16-Lattice!E6/Inputs!$B$5-Inputs!$B$6)-Inputs!$B$17 | F7: =Inputs!$B$15*(Inputs!$B$16-Lattice!F6/Inputs!$B$5-Inputs!$B$6)-Inputs!$B$17 | G7: =Inputs!$B$15*(Inputs!$B$16-Lattice!G6/Inputs!$B$5-Inputs!$B$6)-Inputs!$B$17
E8: =Inputs!$B$15*(Inputs!$B$16-Lattice!E7/Inputs!$B$5-Inputs!$B$6)-Inputs!$B$17 | F8: =Inputs!$B$15*(Inputs!$B$16-Lattice!F7/Inputs!$B$5-Inputs!$B$6)-Inputs!$B$17 | G8: =Inputs!$B$15*(Inputs!$B$16-Lattice!G7/Inputs!$B$5-Inputs!$B$6)-Inputs!$B$17
F9: =Inputs!$B$15*(Inputs!$B$16-Lattice!F8/Inputs!$B$5-Inputs!$B$6)-Inputs!$B$17 | G9: =Inputs!$B$15*(Inputs!$B$16-Lattice!G8/Inputs!$B$5-Inputs!$B$6)-Inputs!$B$17
G10: =Inputs!$B$15*(Inputs!$B$16-Lattice!G9/Inputs!$B$5-Inputs!$B$6)-Inputs!$B$17
A12: EV annual cash flow (constant, no diesel-price exposure)
A13: EV_CF | B13: =Inputs!$B$15*(Inputs!$B$16-Inputs!$B$27*Inputs!$B$12-Inputs!$B$13)-Inputs!$B$17
A15: Value of buying an EV truck at year t, invest_EV(t) | B15: Year 0 | C15: Year 1 | D15: Year 2 | E15: Year 3 | F15: Year 4 | G15: Year 5
B16: =-Inputs!$B$8-Inputs!$B$9+$B$13*(1-(1+Inputs!$B$18)^-8)/Inputs!$B$18 | C16: =-Inputs!$B$8-Inputs!$B$9+$B$13*(1-(1+Inputs!$B$18)^-8)/Inputs!$B$18 | D16: =-Inputs!$B$8-Inputs!$B$9+$B$13*(1-(1+Inputs!$B$18)^-8)/Inputs!$B$18 | E16: =-Inputs!$B$8-Inputs!$B$9+$B$13*(1-(1+Inputs!$B$18)^-8)/Inputs!$B$18 | F16: =-Inputs!$B$8-Inputs!$B$9+$B$13*(1-(1+Inputs!$B$18)^-8)/Inputs!$B$18 | G16: =-Inputs!$B$8-Inputs!$B$9+$B$13*(1-(1+Inputs!$B$18)^-8)/Inputs!$B$18
A18: Value of buying a diesel truck at node (t,i), invest_diesel(t,i) | B18: Year 0 | C18: Year 1 | D18: Year 2 | E18: Year 3 | F18: Year 4 | G18: Year 5
B19: =-Inputs!$B$4+B5*(1-(1+Inputs!$B$18)^-8)/Inputs!$B$18 | C19: =-Inputs!$B$4+C5*(1-(1+Inputs!$B$18)^-8)/Inputs!$B$18 | D19: =-Inputs!$B$4+D5*(1-(1+Inputs!$B$18)^-8)/Inputs!$B$18 | E19: =-Inputs!$B$4+E5*(1-(1+Inputs!$B$18)^-8)/Inputs!$B$18 | F19: =-Inputs!$B$4+F5*(1-(1+Inputs!$B$18)^-8)/Inputs!$B$18 | G19: =-Inputs!$B$4+G5*(1-(1+Inputs!$B$18)^-8)/Inputs!$B$18
C20: =-Inputs!$B$4+C6*(1-(1+Inputs!$B$18)^-8)/Inputs!$B$18 | D20: =-Inputs!$B$4+D6*(1-(1+Inputs!$B$18)^-8)/Inputs!$B$18 | E20: =-Inputs!$B$4+E6*(1-(1+Inputs!$B$18)^-8)/Inputs!$B$18 | F20: =-Inputs!$B$4+F6*(1-(1+Inputs!$B$18)^-8)/Inputs!$B$18 | G20: =-Inputs!$B$4+G6*(1-(1+Inputs!$B$18)^-8)/Inputs!$B$18
D21: =-Inputs!$B$4+D7*(1-(1+Inputs!$B$18)^-8)/Inputs!$B$18 | E21: =-Inputs!$B$4+E7*(1-(1+Inputs!$B$18)^-8)/Inputs!$B$18 | F21: =-Inputs!$B$4+F7*(1-(1+Inputs!$B$18)^-8)/Inputs!$B$18 | G21: =-Inputs!$B$4+G7*(1-(1+Inputs!$B$18)^-8)/Inputs!$B$18
E22: =-Inputs!$B$4+E8*(1-(1+Inputs!$B$18)^-8)/Inputs!$B$18 | F22: =-Inputs!$B$4+F8*(1-(1+Inputs!$B$18)^-8)/Inputs!$B$18 | G22: =-Inputs!$B$4+G8*(1-(1+Inputs!$B$18)^-8)/Inputs!$B$18
F23: =-Inputs!$B$4+F9*(1-(1+Inputs!$B$18)^-8)/Inputs!$B$18 | G23: =-Inputs!$B$4+G9*(1-(1+Inputs!$B$18)^-8)/Inputs!$B$18
G24: =-Inputs!$B$4+G10*(1-(1+Inputs!$B$18)^-8)/Inputs!$B$18
A26: Decision value: best of {buy EV now, buy diesel now, wait}, decision_value(t,i) | B26: Year 0 | C26: Year 1 | D26: Year 2 | E26: Year 3 | F26: Year 4 | G26: Year 5
B27: =MAX($B$16,B19,((Inputs!$B$26*C27+(1-Inputs!$B$26)*C28)/(1+Inputs!$B$18))) | C27: =MAX($C$16,C19,((Inputs!$B$26*D27+(1-Inputs!$B$26)*D28)/(1+Inputs!$B$18))) | D27: =MAX($D$16,D19,((Inputs!$B$26*E27+(1-Inputs!$B$26)*E28)/(1+Inputs!$B$18))) | E27: =MAX($E$16,E19,((Inputs!$B$26*F27+(1-Inputs!$B$26)*F28)/(1+Inputs!$B$18))) | F27: =MAX($F$16,F19,((Inputs!$B$26*G27+(1-Inputs!$B$26)*G28)/(1+Inputs!$B$18))) | G27: =MAX($G$16,G19)
C28: =MAX($C$16,C20,((Inputs!$B$26*D28+(1-Inputs!$B$26)*D29)/(1+Inputs!$B$18))) | D28: =MAX($D$16,D20,((Inputs!$B$26*E28+(1-Inputs!$B$26)*E29)/(1+Inputs!$B$18))) | E28: =MAX($E$16,E20,((Inputs!$B$26*F28+(1-Inputs!$B$26)*F29)/(1+Inputs!$B$18))) | F28: =MAX($F$16,F20,((Inputs!$B$26*G28+(1-Inputs!$B$26)*G29)/(1+Inputs!$B$18))) | G28: =MAX($G$16,G20)
D29: =MAX($D$16,D21,((Inputs!$B$26*E29+(1-Inputs!$B$26)*E30)/(1+Inputs!$B$18))) | E29: =MAX($E$16,E21,((Inputs!$B$26*F29+(1-Inputs!$B$26)*F30)/(1+Inputs!$B$18))) | F29: =MAX($F$16,F21,((Inputs!$B$26*G29+(1-Inputs!$B$26)*G30)/(1+Inputs!$B$18))) | G29: =MAX($G$16,G21)
E30: =MAX($E$16,E22,((Inputs!$B$26*F30+(1-Inputs!$B$26)*F31)/(1+Inputs!$B$18))) | F30: =MAX($F$16,F22,((Inputs!$B$26*G30+(1-Inputs!$B$26)*G31)/(1+Inputs!$B$18))) | G30: =MAX($G$16,G22)
F31: =MAX($F$16,F23,((Inputs!$B$26*G31+(1-Inputs!$B$26)*G32)/(1+Inputs!$B$18))) | G31: =MAX($G$16,G23)
G32: =MAX($G$16,G24)

Sheet Summary
A1: Strategy comparison: NPV today (Rs)
A3: Strategy | B3: NPV today (Rs)
A4: Buy EV now | B4: =DecisionTree!B16
A5: Buy diesel now (naive default choice) | B5: =DecisionTree!B19
A6: Flexible (best of EV/diesel/wait, decided optimally) | B6: =DecisionTree!B27
A7: Value of flexibility (option value) | B7: =DecisionTree!B27-MAX(DecisionTree!B16,DecisionTree!B19)
A9: At India's real calibrated volatility (~7%/yr), this comes out at or near zero: diesel's current cost advantage is large enough, and volatility low enough, that waiting to decide is not worth the foregone diesel profit -- buy the current best option now, and revisit for the NEXT truck purchase. See Sensitivity for how this changes at higher volatility.

Sheet Sensitivity
A1: Simplified one-year option value vs volatility
A2: A single-period version of the same logic (not the full 5-year tree): if sigma were higher than India's real calibrated 7%, would waiting one year become worthwhile? This isolates the volatility effect on its own -- drift (mu) and every cost input stay fixed at their real values throughout.
A4: Sigma (annual) | B4: u | C4: d | D4: p(up) | E4: Diesel price up | F4: Diesel price down | G4: Commit now | H4: Wait 1yr, decide next | I4: Option value
A5: 0.07 | B5: =EXP(A5) | C5: =1/B5 | D5: =(EXP(Inputs!$B$22)-C5)/(B5-C5) | E5: =Inputs!$B$20*B5 | F5: =Inputs!$B$20*C5 | G5: =MAX(DecisionTree!$B$16,DecisionTree!$B$19) | H5: =(D5*MAX(DecisionTree!$B$16,(-Inputs!$B$4+(Inputs!$B$15*(Inputs!$B$16-E5/Inputs!$B$5-Inputs!$B$6)-Inputs!$B$17)*(1-(1+Inputs!$B$18)^-8)/Inputs!$B$18))+(1-D5)*MAX(DecisionTree!$B$16,(-Inputs!$B$4+(Inputs!$B$15*(Inputs!$B$16-F5/Inputs!$B$5-Inputs!$B$6)-Inputs!$B$17)*(1-(1+Inputs!$B$18)^-8)/Inputs!$B$18)))/(1+Inputs!$B$18) | I5: =MAX(G5,H5)-G5
A6: 0.1 | B6: =EXP(A6) | C6: =1/B6 | D6: =(EXP(Inputs!$B$22)-C6)/(B6-C6) | E6: =Inputs!$B$20*B6 | F6: =Inputs!$B$20*C6 | G6: =MAX(DecisionTree!$B$16,DecisionTree!$B$19) | H6: =(D6*MAX(DecisionTree!$B$16,(-Inputs!$B$4+(Inputs!$B$15*(Inputs!$B$16-E6/Inputs!$B$5-Inputs!$B$6)-Inputs!$B$17)*(1-(1+Inputs!$B$18)^-8)/Inputs!$B$18))+(1-D6)*MAX(DecisionTree!$B$16,(-Inputs!$B$4+(Inputs!$B$15*(Inputs!$B$16-F6/Inputs!$B$5-Inputs!$B$6)-Inputs!$B$17)*(1-(1+Inputs!$B$18)^-8)/Inputs!$B$18)))/(1+Inputs!$B$18) | I6: =MAX(G6,H6)-G6
A7: 0.15 | B7: =EXP(A7) | C7: =1/B7 | D7: =(EXP(Inputs!$B$22)-C7)/(B7-C7) | E7: =Inputs!$B$20*B7 | F7: =Inputs!$B$20*C7 | G7: =MAX(DecisionTree!$B$16,DecisionTree!$B$19) | H7: =(D7*MAX(DecisionTree!$B$16,(-Inputs!$B$4+(Inputs!$B$15*(Inputs!$B$16-E7/Inputs!$B$5-Inputs!$B$6)-Inputs!$B$17)*(1-(1+Inputs!$B$18)^-8)/Inputs!$B$18))+(1-D7)*MAX(DecisionTree!$B$16,(-Inputs!$B$4+(Inputs!$B$15*(Inputs!$B$16-F7/Inputs!$B$5-Inputs!$B$6)-Inputs!$B$17)*(1-(1+Inputs!$B$18)^-8)/Inputs!$B$18)))/(1+Inputs!$B$18) | I7: =MAX(G7,H7)-G7
A8: 0.2 | B8: =EXP(A8) | C8: =1/B8 | D8: =(EXP(Inputs!$B$22)-C8)/(B8-C8) | E8: =Inputs!$B$20*B8 | F8: =Inputs!$B$20*C8 | G8: =MAX(DecisionTree!$B$16,DecisionTree!$B$19) | H8: =(D8*MAX(DecisionTree!$B$16,(-Inputs!$B$4+(Inputs!$B$15*(Inputs!$B$16-E8/Inputs!$B$5-Inputs!$B$6)-Inputs!$B$17)*(1-(1+Inputs!$B$18)^-8)/Inputs!$B$18))+(1-D8)*MAX(DecisionTree!$B$16,(-Inputs!$B$4+(Inputs!$B$15*(Inputs!$B$16-F8/Inputs!$B$5-Inputs!$B$6)-Inputs!$B$17)*(1-(1+Inputs!$B$18)^-8)/Inputs!$B$18)))/(1+Inputs!$B$18) | I8: =MAX(G8,H8)-G8
A9: 0.25 | B9: =EXP(A9) | C9: =1/B9 | D9: =(EXP(Inputs!$B$22)-C9)/(B9-C9) | E9: =Inputs!$B$20*B9 | F9: =Inputs!$B$20*C9 | G9: =MAX(DecisionTree!$B$16,DecisionTree!$B$19) | H9: =(D9*MAX(DecisionTree!$B$16,(-Inputs!$B$4+(Inputs!$B$15*(Inputs!$B$16-E9/Inputs!$B$5-Inputs!$B$6)-Inputs!$B$17)*(1-(1+Inputs!$B$18)^-8)/Inputs!$B$18))+(1-D9)*MAX(DecisionTree!$B$16,(-Inputs!$B$4+(Inputs!$B$15*(Inputs!$B$16-F9/Inputs!$B$5-Inputs!$B$6)-Inputs!$B$17)*(1-(1+Inputs!$B$18)^-8)/Inputs!$B$18)))/(1+Inputs!$B$18) | I9: =MAX(G9,H9)-G9
A10: 0.3 | B10: =EXP(A10) | C10: =1/B10 | D10: =(EXP(Inputs!$B$22)-C10)/(B10-C10) | E10: =Inputs!$B$20*B10 | F10: =Inputs!$B$20*C10 | G10: =MAX(DecisionTree!$B$16,DecisionTree!$B$19) | H10: =(D10*MAX(DecisionTree!$B$16,(-Inputs!$B$4+(Inputs!$B$15*(Inputs!$B$16-E10/Inputs!$B$5-Inputs!$B$6)-Inputs!$B$17)*(1-(1+Inputs!$B$18)^-8)/Inputs!$B$18))+(1-D10)*MAX(DecisionTree!$B$16,(-Inputs!$B$4+(Inputs!$B$15*(Inputs!$B$16-F10/Inputs!$B$5-Inputs!$B$6)-Inputs!$B$17)*(1-(1+Inputs!$B$18)^-8)/Inputs!$B$18)))/(1+Inputs!$B$18) | I10: =MAX(G10,H10)-G10
A11: 0.35 | B11: =EXP(A11) | C11: =1/B11 | D11: =(EXP(Inputs!$B$22)-C11)/(B11-C11) | E11: =Inputs!$B$20*B11 | F11: =Inputs!$B$20*C11 | G11: =MAX(DecisionTree!$B$16,DecisionTree!$B$19) | H11: =(D11*MAX(DecisionTree!$B$16,(-Inputs!$B$4+(Inputs!$B$15*(Inputs!$B$16-E11/Inputs!$B$5-Inputs!$B$6)-Inputs!$B$17)*(1-(1+Inputs!$B$18)^-8)/Inputs!$B$18))+(1-D11)*MAX(DecisionTree!$B$16,(-Inputs!$B$4+(Inputs!$B$15*(Inputs!$B$16-F11/Inputs!$B$5-Inputs!$B$6)-Inputs!$B$17)*(1-(1+Inputs!$B$18)^-8)/Inputs!$B$18)))/(1+Inputs!$B$18) | I11: =MAX(G11,H11)-G11
A12: 0.4 | B12: =EXP(A12) | C12: =1/B12 | D12: =(EXP(Inputs!$B$22)-C12)/(B12-C12) | E12: =Inputs!$B$20*B12 | F12: =Inputs!$B$20*C12 | G12: =MAX(DecisionTree!$B$16,DecisionTree!$B$19) | H12: =(D12*MAX(DecisionTree!$B$16,(-Inputs!$B$4+(Inputs!$B$15*(Inputs!$B$16-E12/Inputs!$B$5-Inputs!$B$6)-Inputs!$B$17)*(1-(1+Inputs!$B$18)^-8)/Inputs!$B$18))+(1-D12)*MAX(DecisionTree!$B$16,(-Inputs!$B$4+(Inputs!$B$15*(Inputs!$B$16-F12/Inputs!$B$5-Inputs!$B$6)-Inputs!$B$17)*(1-(1+Inputs!$B$18)^-8)/Inputs!$B$18)))/(1+Inputs!$B$18) | I12: =MAX(G12,H12)-G12
A13: 0.43 | B13: =EXP(A13) | C13: =1/B13 | D13: =(EXP(Inputs!$B$22)-C13)/(B13-C13) | E13: =Inputs!$B$20*B13 | F13: =Inputs!$B$20*C13 | G13: =MAX(DecisionTree!$B$16,DecisionTree!$B$19) | H13: =(D13*MAX(DecisionTree!$B$16,(-Inputs!$B$4+(Inputs!$B$15*(Inputs!$B$16-E13/Inputs!$B$5-Inputs!$B$6)-Inputs!$B$17)*(1-(1+Inputs!$B$18)^-8)/Inputs!$B$18))+(1-D13)*MAX(DecisionTree!$B$16,(-Inputs!$B$4+(Inputs!$B$15*(Inputs!$B$16-F13/Inputs!$B$5-Inputs!$B$6)-Inputs!$B$17)*(1-(1+Inputs!$B$18)^-8)/Inputs!$B$18)))/(1+Inputs!$B$18) | I13: =MAX(G13,H13)-G13
A15: Option value is exactly Rs 0 through India's real sigma (7%) and stays flat until sigma crosses roughly 38-40% -- only past that point does waiting start to beat committing now. Crude oil itself runs at ~43% annual volatility, so a market with that much price risk (unlike India's administered diesel pricing) is exactly where flexibility would start to be worth paying for -- the classic real-options result made concrete with real numbers.
